sqlalchemy_helper_tool/__init__.py
sqlalchemy_helper_tool/sqlalchemy_helper_tool.py
sqlalchemy_helper_tool-1.7.3.dist-info/licenses/LICENSE.txt
sqlalchemy_helper_tool-1.7.3.dist-info/METADATA
sqlalchemy_helper_tool-1.7.3.dist-info/WHEEL
sqlalchemy_helper_tool-1.7.3.dist-info/top_level.txt
sqlalchemy_helper_tool-1.7.3.dist-info/RECORD
