Metadata-Version: 2.4
Name: sqlalchemy_helper_tool
Version: 1.7.3
Summary: Package to work with mysql database from python
Author-email: Anabel Reyes <anakings95@gmail.com>
Maintainer-email: Anabel Reyes <anakings95@gmail.com>
License: Copyright 2025 Anabel Reyes
Project-URL: Homepage, https://github.com/anakings/sqlalchemy_helper_tool
Project-URL: Documentation, https://github.com/anakings/sqlalchemy_helper_tool/blob/feature/sqlalchemy_helper_tool/README.md
Keywords: Database
Requires-Python: >=3.7
License-File: LICENSE.txt
Requires-Dist: SQLAlchemy==1.4.39
Requires-Dist: pandas==2.1.1
Requires-Dist: numpy==1.26.1
Requires-Dist: PyMySQL==1.0.3
Requires-Dist: pyodbc>=4.0.39
Dynamic: license-file
